pengeomgen/__init__.py
pengeomgen/blocks/__init__.py
pengeomgen/blocks/base.py
pengeomgen/blocks/body.py
pengeomgen/blocks/clone.py
pengeomgen/blocks/end.py
pengeomgen/blocks/include.py
pengeomgen/blocks/module.py
pengeomgen/blocks/surface.py
pengeomgen-0.0.2.dist-info/METADATA
pengeomgen-0.0.2.dist-info/RECORD
pengeomgen-0.0.2.dist-info/WHEEL
pengeomgen-0.0.2.dist-info/top_level.txt
