Metadata-Version: 2.1
Name: pengeomgen
Version: 0.0.2
Summary: An easy geometry-definition file generator for PENELOPE PENGEOM
Home-page: https://github.com/Toni-SM/pengeomgen
Author: Antonio Serrano
Author-email: toni.sm91@gmail.com
License: UNKNOWN
Platform: UNKNOWN
Classifier: Programming Language :: Python :: 3
Classifier: License :: OSI Approved :: MIT License
Classifier: Operating System :: OS Independent
